<?xml version="1.0" encoding="UTF-8"?>
<ConnList sysname="Power Seat"><item type="conn" code="P16"><note></note><partNo>90980-10997</partNo></item><item type="conn" code="P17"><note></note><partNo>90980-10997</partNo></item><item type="conn" code="P18"><note></note><partNo>90980-10825</partNo></item><item type="conn" code="P19"><note></note><partNo>90980-10825</partNo></item><item type="conn" code="P20"><note></note><partNo>90980-10825</partNo></item><item type="conn" code="P21"><note></note><partNo>90980-10825</partNo></item><item type="conn" code="P22"><note></note><partNo>90980-10825</partNo></item><item type="conn" code="P23"><note></note><partNo>90980-10825</partNo></item><item type="conn" code="P24"><note></note><partNo>90980-10825</partNo></item><item type="conn" code="P25"><note></note><partNo>90980-10825</partNo></item></ConnList>
